rfc3987_syntax/CITATION.cff
rfc3987_syntax/__init__.py
rfc3987_syntax/syntax_helpers.py
rfc3987_syntax/syntax_rfc3987.lark
rfc3987_syntax/utils.py
rfc3987_syntax-1.0.0.dist-info/METADATA
rfc3987_syntax-1.0.0.dist-info/WHEEL
rfc3987_syntax-1.0.0.dist-info/licenses/LICENSE
rfc3987_syntax-1.0.0.dist-info/RECORD
