Metadata-Version: 2.4
Name: rfc3987-syntax
Version: 1.0.0
Summary: Helper functions to syntactically validate strings according to RFC 3987.
Project-URL: Homepage, https://github.com/willynilly/rfc3987-syntax
Project-URL: Documentation, https://github.com/willynilly/rfc3987-syntax#readme
Project-URL: Issues, https://github.com/willynilly/rfc3987-syntax/issues
Project-URL: Source, https://github.com/willynilly/rfc3987-syntax
Author-email: Will Riley <wanderingwill@gmail.com>
License-Expression: MIT
License-File: LICENSE
Keywords: RFC 3987,RFC3987,parser,syntax,validator
Classifier: Development Status :: 3 - Alpha
Classifier: Intended Audience :: Developers
Classifier: Intended Audience :: Education
Classifier: Intended Audience :: Information Technology
Classifier: Intended Audience :: Science/Research
Classifier: Intended Audience :: System Administrators
Classifier: License :: OSI Approved :: Apache Software License
Classifier: Natural Language :: English
Classifier: Programming Language :: Python
Classifier: Programming Language :: Python :: 3
Classifier: Programming Language :: Python :: 3.9
Classifier: Topic :: Scientific/Engineering
Classifier: Topic :: Software Development
Classifier: Topic :: Utilities
Requires-Python: >=3.9
Requires-Dist: lark>=1.2.2
Provides-Extra: testing
Requires-Dist: pytest>=8.3.5; extra == 'testing'
